<fix major='4' minor='2'>
	<messages>
		<message name='NewOrderSingle' msgtype='D' msgcat='app'>
			<field number='1' name='Account' required='N'/>
			<field number='8' name='BeginString ' required='Y'/>
			<field number='11' name='ClOrdID' required='Y'/>
			<field number='12' name='Commission' required='N'/>
			<field number='13' name='CommType' required='N'/>
			<field number='15' name='Currency' required='N'/>
			<field number='18' name='ExecInst' required='N'/>
			<field number='21' name='HandlInst' required='Y'/>
			<field number='22' name='IDSource' required='N'/>
			<field number='23' name='IOIid' required='N'/>
			<field number='38' name='OrderQty' required='N'/>
			<field number='40' name='OrdType' required='Y'/>
			<field number='44' name='Price' required='N'/>
			<field number='47' name='Rule80A' required='N'/>
			<field number='48' name='SecurityID' required='N'/>
			<field number='50' name='SenderSubID' required='N'/>
			<field number='54' name='Side' required='Y'/>
			<field number='55' name='Symbol' required='Y'/>
			<field number='59' name='TimeInForce' required='N'/>
			<field number='58' name='Text' required='N'/>
			<field number='60' name='TransactTime' required='Y'/>
			<field number='63' name='SettlmntTyp' required='N'/>
			<field number='64' name='FutSettDate' required='N'/>
			<field number='65' name='SymbolSfx' required='N'/>
			<field number='76' name='ExecBroker' required='N'/>
			<field number='77' name='OpenClose' required='N'/>
			<field number='78' name='NoAllocs' required='N'/>
			<field number='81' name='ProcessCode' required='N'/>
			<field number='99' name='StopPx' required='N'/>
			<field number='100' name='ExDestination' required='N'/>
			<field number='106' name='Issuer' required='N'/>
			<field number='107' name='SecurityDesc' required='N'/>
			<field number='109' name='ClientID' required='N'/>
			<field number='110' name='MinQty' required='N'/>
			<field number='111' name='MaxFloor' required='N'/>
			<field number='114' name='LocateReqd' required='N'/>
			<field number='115' name='OnBehalfOfCompID' required='N'/>
			<field number='117' name='QuoteID' required='N'/>
			<field number='120' name='SettlCurrency' required='N'/>
			<field number='121' name='ForexReq' required='N'/>
			<field number='126' name='ExpireTime' required='N'/>
			<field number='140' name='PrevClosePx' required='N'/>
			<field number='152' name='CashOrderQty' required='N'/>
			<field number='167' name='SecurityType' required='N'/>
			<field number='168' name='EffectiveTime' required='N'/>
			<field number='192' name='OrderQty2' required='N'/>
			<field number='193' name='FutSettDate2' required='N'/>
			<field number='200' name='MaturityMonthYear' required='N'/>
			<field number='201' name='PutOrCall' required='N'/>
			<field number='202' name='StrikePrice' required='N'/>
			<field number='203' name='CoveredOrUncovered' required='N'/>
			<field number='204' name='CustomerOrFirm' required='N'/>
			<field number='205' name='MaturityDay' required='N'/>
			<field number='206' name='OptAttribute' required='N'/>
			<field number='207' name='SecurityExchange' required='N'/>
			<field number='210' name='MaxShow' required='N'/>
			<field number='211' name='PegDifference' required='N'/>
			<field number='223' name='CouponRate' required='N'/>
			<field number='231' name='ContractMultiplier' required='N'/>
			<field number='348' name='EncodedIssuerLen' required='N'/>
			<field number='349' name='EncodedIssuer' required='N'/>
			<field number='350' name='EncodedSecurityDescLen' required='N'/>
			<field number='351' name='EncodedSecurityDesc' required='N'/>
			<field number='354' name='EncodedTextLen' required='N'/>
			<field number='355' name='EncodedText' required='N'/>
			<field number='376' name='ComplianceID' required='N'/>
			<field number='377' name='SolicitedFlag' required='N'/>
			<field number='388' name='DiscretionInst' required='N'/>
			<field number='389' name='DiscretionOffsetValue' required='N'/>
			<field number='427' name='GTBookingInst' required='N'/>
			<field number='432' name='ExpireDate' required='N'/>
			<field number='439' name='ClearingFirm' required='N'/>
			<field number='440' name='ClearingAccount' required='N'/>
			<field number='9049' name='FlexUser' required='N'/>
			<field number='9050' name='StartTime' required='N'/>
			<field number='9051' name='EndTime' required='N'/>
			<field number='9052' name='StrategyName' required='N'/>
			<field number='9053' name='MinPctVolume' required='N'/>
			<field number='9054' name='MaxPctVolume' required='N'/>
			<field number='9055' name='BenchPrice' required='N'/>
			<field number='9056' name='ExecutionStyle' required='N'/>
			<field number='9057' name='ExcludeAuction' required='N'/>
			<field number='9058' name='SweepLit' required='N'/>
			<field number='9059' name='OBType' required='N'/>
			<field number='9060' name='WouldLevel' required='N'/>
			<field number='9061' name='WouldDark' required='N'/>
			<field number='9062' name='AuctionPct' required='N'/>
			<field number='9063' name='PgtName' required='N'/>
			<field number='9064' name='MinSize' required='N'/>
			<field number='9065' name='AggregatedStyle' required='N'/>
			<field number='9066' name='TickerTrading' required='N'/>
		</message>
	</messages>
</fix>